FlowIO-0.9.13.data/data/LICENSE
flowio/__init__.py
flowio/create_fcs.py
flowio/flowdata.py
FlowIO-0.9.13.dist-info/LICENSE
FlowIO-0.9.13.dist-info/METADATA
FlowIO-0.9.13.dist-info/WHEEL
FlowIO-0.9.13.dist-info/top_level.txt
FlowIO-0.9.13.dist-info/RECORD
