Metadata-Version: 2.1
Name: FlowIO
Version: 0.9.13
Summary: FlowIO is a Python library for reading / writing Flow Cytometry Standard (FCS) files
Home-page: https://github.com/whitews/flowio
Author: Scott White
Author-email: whitews@gmail.com
License: BSD
Platform: UNKNOWN
Classifier: Programming Language :: Python :: 3.9
Classifier: Programming Language :: Python :: 3.8
Classifier: Programming Language :: Python :: 3.7
Classifier: Programming Language :: Python :: 3.6
License-File: LICENSE
